SVAR/MoG.py
SVAR/SVARbasics.py
SVAR/SVARutil.py
SVAR/SVARutilGMM.py
SVAR/__init__.py
SVAR/estOutput.py
SVAR/estPrepare.py
SVAR/estSVAR.py
SVAR/estSVARbootstrap.py
SVAR/estimatorCholesky.py
SVAR/estimatorGMM.py
SVAR/estimatorGMMW.py
SVAR/estimatorGMMWF.py
SVAR/estimatorPML.py
svarpy-0.1.17.dist-info/licenses/LICENSE
svarpy-0.1.17.dist-info/METADATA
svarpy-0.1.17.dist-info/WHEEL
svarpy-0.1.17.dist-info/top_level.txt
svarpy-0.1.17.dist-info/RECORD
