Metadata-Version: 2.4
Name: SVARpy
Version: 0.1.17
Summary: SVAR estimation
Home-page: https://github.com/Saschakew/SVARpy
Author: Sascha Keweloh
Author-email: sascha.keweloh@tu-dortmund.de
License: MIT License
Classifier: Programming Language :: Python :: 3
Classifier: License :: OSI Approved :: MIT License
Classifier: Operating System :: OS Independent
Requires-Python: >=3.7
License-File: LICENSE
Dynamic: author
Dynamic: author-email
Dynamic: classifier
Dynamic: description
Dynamic: description-content-type
Dynamic: home-page
Dynamic: license
Dynamic: license-file
Dynamic: requires-python
Dynamic: summary
